llama_index/readers/pebblo/__init__.py
llama_index/readers/pebblo/base.py
llama_index/readers/pebblo/utility.py
llama_index_readers_pebblo-0.5.1.dist-info/METADATA
llama_index_readers_pebblo-0.5.1.dist-info/WHEEL
llama_index_readers_pebblo-0.5.1.dist-info/licenses/LICENSE
llama_index_readers_pebblo-0.5.1.dist-info/RECORD
