Metadata-Version: 2.4
Name: llama-index-readers-pebblo
Version: 0.5.1
Summary: llama-index readers pebblo integration
Author-email: Yograj Shisode <yograj.shisode@opcito.com>
License-Expression: MIT
License-File: LICENSE
Requires-Python: <4.0,>=3.9
Requires-Dist: llama-index-core<0.15,>=0.13.0
Requires-Dist: llama-index-readers-file<0.6,>=0.5.0
